{
  "images": [
    {
      "url": "images/1.jpg",
      "label": "1"
    },
    {
      "url": "images/2.jpg",
      "label": "2"
    },
    {
      "url": "images/3.jpg",
      "label": "3"
    },
    {
      "url": "images/4.jpg",
      "label": "4"
    },
    {
      "url": "images/5.jpg",
      "label": "5"
    },
    {
      "url": "images/6.jpg",
      "label": "6"
    },
    {
      "url": "images/7.jpg",
      "label": "7"
    },
    {
      "url": "images/8.jpg",
      "label": "8"
    },
    {
      "url": "images/9.jpg",
      "label": "9"
    },
    {
      "url": "images/10.jpg",
      "label": "10"
    },
    {
      "url": "images/11.jpg",
      "label": "11"
    },
    {
      "url": "images/12.jpg",
      "label": "12"
    },
    {
      "url": "images/13.jpg",
      "label": "13"
    },
    {
      "url": "images/14.jpg",
      "label": "14"
    },
    {
      "url": "images/15.jpg",
      "label": "15"
    },
    {
      "url": "images/16.jpg",
      "label": "16"
    },
    {
      "url": "images/17.jpg",
      "label": "17"
    },
    {
      "url": "images/18.jpg",
      "label": "18"
    },
    {
      "url": "images/19.jpg",
      "label": "19"
    },
    {
      "url": "images/20.jpg",
      "label": "20"
    },
    {
      "url": "images/21.jpg",
      "label": "21"
    },
    {
      "url": "images/22.jpg",
      "label": "22"
    },
    {
      "url": "images/23.jpg",
      "label": "23"
    },
    {
      "url": "images/24.jpg",
      "label": "24"
    },
    {
      "url": "images/25.jpg",
      "label": "25"
    },
    {
      "url": "images/26.jpg",
      "label": "26"
    },
    {
      "url": "images/27.jpg",
      "label": "27"
    },
    {
      "url": "images/28.jpg",
      "label": "28"
    },
    {
      "url": "images/29.jpg",
      "label": "29"
    },
    {
      "url": "images/30.jpg",
      "label": "30"
    },
    {
      "url": "images/31.jpg",
      "label": "31"
    },
    {
      "url": "images/32.jpg",
      "label": "32"
    },
    {
      "url": "images/33.jpg",
      "label": "33"
    },
    {
      "url": "images/34.jpg",
      "label": "34"
    },
    {
      "url": "images/35.jpg",
      "label": "35"
    },
    {
      "url": "images/36.jpg",
      "label": "36"
    },
    {
      "url": "images/37.jpg",
      "label": "37"
    },
    {
      "url": "images/38.jpg",
      "label": "38"
    },
    {
      "url": "images/39.jpg",
      "label": "39"
    },
    {
      "url": "images/40.jpg",
      "label": "40"
    },
    {
      "url": "images/41.jpg",
      "label": "41"
    },
    {
      "url": "images/42.jpg",
      "label": "42"
    },
    {
      "url": "images/43.jpg",
      "label": "43"
    },
    {
      "url": "images/44.jpg",
      "label": "44"
    },
    {
      "url": "images/45.jpg",
      "label": "45"
    },
    {
      "url": "images/46.jpg",
      "label": "46"
    },
    {
      "url": "images/47.jpg",
      "label": "47"
    },
    {
      "url": "images/48.jpg",
      "label": "48"
    },
    {
      "url": "images/49.jpg",
      "label": "49"
    },
    {
      "url": "images/50.jpg",
      "label": "50"
    },
    {
      "url": "images/51.jpg",
      "label": "51"
    },
    {
      "url": "images/52.jpg",
      "label": "52"
    },
    {
      "url": "images/53.jpg",
      "label": "53"
    },
    {
      "url": "images/54.jpg",
      "label": "54"
    },
    {
      "url": "images/55.jpg",
      "label": "55"
    },
    {
      "url": "images/56.jpg",
      "label": "56"
    },
    {
      "url": "images/57.jpg",
      "label": "57"
    },
    {
      "url": "images/58.jpg",
      "label": "58"
    },
    {
      "url": "images/59.jpg",
      "label": "59"
    },
    {
      "url": "images/60.jpg",
      "label": "60"
    },
    {
      "url": "images/61.jpg",
      "label": "61"
    },
    {
      "url": "images/62.jpg",
      "label": "62"
    },
    {
      "url": "images/63.jpg",
      "label": "63"
    },
    {
      "url": "images/64.jpg",
      "label": "64"
    },
    {
      "url": "images/65.jpg",
      "label": "65"
    },
    {
      "url": "images/66.jpg",
      "label": "66"
    },
    {
      "url": "images/67.jpg",
      "label": "67"
    },
    {
      "url": "images/68.jpg",
      "label": "68"
    },
    {
      "url": "images/69.jpg",
      "label": "69"
    },
    {
      "url": "images/70.jpg",
      "label": "70"
    },
    {
      "url": "images/71.jpg",
      "label": "71"
    },
    {
      "url": "images/72.jpg",
      "label": "72"
    },
    {
      "url": "images/73.jpg",
      "label": "73"
    },
    {
      "url": "images/74.jpg",
      "label": "74"
    },
    {
      "url": "images/75.jpg",
      "label": "75"
    },
    {
      "url": "images/76.jpg",
      "label": "76"
    },
    {
      "url": "images/77.jpg",
      "label": "77"
    },
    {
      "url": "images/78.jpg",
      "label": "78"
    },
    {
      "url": "images/79.jpg",
      "label": "79"
    },
    {
      "url": "images/80.jpg",
      "label": "80"
    },
    {
      "url": "images/81.jpg",
      "label": "81"
    },
    {
      "url": "images/82.jpg",
      "label": "82"
    },
    {
      "url": "images/83.jpg",
      "label": "83"
    },
    {
      "url": "images/84.jpg",
      "label": "84"
    },
    {
      "url": "images/85.jpg",
      "label": "85"
    },
    {
      "url": "images/86.jpg",
      "label": "86"
    },
    {
      "url": "images/87.jpg",
      "label": "87"
    },
    {
      "url": "images/88.jpg",
      "label": "88"
    },
    {
      "url": "images/89.jpg",
      "label": "89"
    },
    {
      "url": "images/90.jpg",
      "label": "90"
    },
    {
      "url": "images/91.jpg",
      "label": "91"
    },
    {
      "url": "images/92.jpg",
      "label": "92"
    },
    {
      "url": "images/93.jpg",
      "label": "93"
    },
    {
      "url": "images/94.jpg",
      "label": "94"
    },
    {
      "url": "images/95.jpg",
      "label": "95"
    },
    {
      "url": "images/96.jpg",
      "label": "96"
    },
    {
      "url": "images/97.jpg",
      "label": "97"
    },
    {
      "url": "images/98.jpg",
      "label": "98"
    },
    {
      "url": "images/99.jpg",
      "label": "99"
    },
    {
      "url": "images/100.jpg",
      "label": "100"
    },
    {
      "url": "images/101.jpg",
      "label": "101"
    },
    {
      "url": "images/102.jpg",
      "label": "102"
    },
    {
      "url": "images/103.jpg",
      "label": "103"
    },
    {
      "url": "images/104.jpg",
      "label": "104"
    },
    {
      "url": "images/105.jpg",
      "label": "105"
    },
    {
      "url": "images/106.jpg",
      "label": "106"
    },
    {
      "url": "images/107.jpg",
      "label": "107"
    },
    {
      "url": "images/108.jpg",
      "label": "108"
    },
    {
      "url": "images/109.jpg",
      "label": "109"
    },
    {
      "url": "images/110.jpg",
      "label": "110"
    },
    {
      "url": "images/111.jpg",
      "label": "111"
    },
    {
      "url": "images/112.jpg",
      "label": "112"
    },
    {
      "url": "images/113.jpg",
      "label": "113"
    },
    {
      "url": "images/114.jpg",
      "label": "114"
    },
    {
      "url": "images/115.jpg",
      "label": "115"
    },
    {
      "url": "images/116.jpg",
      "label": "116"
    },
    {
      "url": "images/117.jpg",
      "label": "117"
    },
    {
      "url": "images/118.jpg",
      "label": "118"
    },
    {
      "url": "images/119.jpg",
      "label": "119"
    },
    {
      "url": "images/120.jpg",
      "label": "120"
    },
    {
      "url": "images/121.jpg",
      "label": "121"
    },
    {
      "url": "images/122.jpg",
      "label": "122"
    },
    {
      "url": "images/123.jpg",
      "label": "123"
    },
    {
      "url": "images/124.jpg",
      "label": "124"
    },
    {
      "url": "images/125.jpg",
      "label": "125"
    },
    {
      "url": "images/126.jpg",
      "label": "126"
    },
    {
      "url": "images/127.jpg",
      "label": "127"
    },
    {
      "url": "images/128.jpg",
      "label": "128"
    },
    {
      "url": "images/129.jpg",
      "label": "129"
    },
    {
      "url": "images/130.jpg",
      "label": "130"
    },
    {
      "url": "images/131.jpg",
      "label": "131"
    },
    {
      "url": "images/132.jpg",
      "label": "132"
    },
    {
      "url": "images/133.jpg",
      "label": "133"
    },
    {
      "url": "images/134.jpg",
      "label": "134"
    },
    {
      "url": "images/135.jpg",
      "label": "135"
    },
    {
      "url": "images/136.jpg",
      "label": "136"
    },
    {
      "url": "images/137.jpg",
      "label": "137"
    },
    {
      "url": "images/138.jpg",
      "label": "138"
    },
    {
      "url": "images/139.jpg",
      "label": "139"
    },
    {
      "url": "images/140.jpg",
      "label": "140"
    },
    {
      "url": "images/141.jpg",
      "label": "141"
    },
    {
      "url": "images/142.jpg",
      "label": "142"
    },
    {
      "url": "images/143.jpg",
      "label": "143"
    },
    {
      "url": "images/144.jpg",
      "label": "144"
    },
    {
      "url": "images/145.jpg",
      "label": "145"
    },
    {
      "url": "images/146.jpg",
      "label": "146"
    },
    {
      "url": "images/147.jpg",
      "label": "147"
    },
    {
      "url": "images/148.jpg",
      "label": "148"
    },
    {
      "url": "images/149.jpg",
      "label": "149"
    },
    {
      "url": "images/150.jpg",
      "label": "150"
    },
    {
      "url": "images/151.jpg",
      "label": "151"
    },
    {
      "url": "images/152.jpg",
      "label": "152"
    },
    {
      "url": "images/153.jpg",
      "label": "153"
    },
    {
      "url": "images/154.jpg",
      "label": "154"
    },
    {
      "url": "images/155.jpg",
      "label": "155"
    },
    {
      "url": "images/156.jpg",
      "label": "156"
    },
    {
      "url": "images/157.jpg",
      "label": "157"
    },
    {
      "url": "images/158.jpg",
      "label": "158"
    },
    {
      "url": "images/159.jpg",
      "label": "159"
    },
    {
      "url": "images/160.jpg",
      "label": "160"
    },
    {
      "url": "images/161.jpg",
      "label": "161"
    },
    {
      "url": "images/162.jpg",
      "label": "162"
    },
    {
      "url": "images/163.jpg",
      "label": "163"
    },
    {
      "url": "images/164.jpg",
      "label": "164"
    },
    {
      "url": "images/165.jpg",
      "label": "165"
    },
    {
      "url": "images/166.jpg",
      "label": "166"
    },
    {
      "url": "images/167.jpg",
      "label": "167"
    },
    {
      "url": "images/168.jpg",
      "label": "168"
    },
    {
      "url": "images/169.jpg",
      "label": "169"
    },
    {
      "url": "images/170.jpg",
      "label": "170"
    },
    {
      "url": "images/171.jpg",
      "label": "171"
    },
    {
      "url": "images/172.jpg",
      "label": "172"
    },
    {
      "url": "images/173.jpg",
      "label": "173"
    },
    {
      "url": "images/174.jpg",
      "label": "174"
    },
    {
      "url": "images/175.jpg",
      "label": "175"
    },
    {
      "url": "images/176.jpg",
      "label": "176"
    },
    {
      "url": "images/177.jpg",
      "label": "177"
    },
    {
      "url": "images/178.jpg",
      "label": "178"
    },
    {
      "url": "images/179.jpg",
      "label": "179"
    },
    {
      "url": "images/180.jpg",
      "label": "180"
    },
    {
      "url": "images/181.jpg",
      "label": "181"
    },
    {
      "url": "images/182.jpg",
      "label": "182"
    },
    {
      "url": "images/183.jpg",
      "label": "183"
    },
    {
      "url": "images/184.jpg",
      "label": "184"
    },
    {
      "url": "images/185.jpg",
      "label": "185"
    },
    {
      "url": "images/186.jpg",
      "label": "186"
    },
    {
      "url": "images/187.jpg",
      "label": "187"
    },
    {
      "url": "images/188.jpg",
      "label": "188"
    },
    {
      "url": "images/189.jpg",
      "label": "189"
    },
    {
      "url": "images/190.jpg",
      "label": "190"
    },
    {
      "url": "images/191.jpg",
      "label": "191"
    },
    {
      "url": "images/192.jpg",
      "label": "192"
    },
    {
      "url": "images/193.jpg",
      "label": "193"
    },
    {
      "url": "images/194.jpg",
      "label": "194"
    },
    {
      "url": "images/195.jpg",
      "label": "195"
    },
    {
      "url": "images/196.jpg",
      "label": "196"
    },
    {
      "url": "images/197.jpg",
      "label": "197"
    },
    {
      "url": "images/198.jpg",
      "label": "198"
    },
    {
      "url": "images/199.jpg",
      "label": "199"
    },
    {
      "url": "images/200.jpg",
      "label": "200"
    },
    {
      "url": "images/201.jpg",
      "label": "201"
    },
    {
      "url": "images/202.jpg",
      "label": "202"
    }
  ]
}